{
  "openapi": "3.0.1",
  "info": {
    "title": "FeedbackService",
    "version": "1.0"
  },
  "paths": {
    "/api/Feedback": {
      "get": {
        "tags": [
          "Feedback"
        ],
        "responses": {
          "200": {
            "description": "OK",
            "content": {
              "text/plain": {
                "schema": {
                  "type": "array",
                  "items": {
                    "$ref": "#/components/schemas/Feedback"
                  }
                }
              },
              "application/json": {
                "schema": {
                  "type": "array",
                  "items": {
                    "$ref": "#/components/schemas/Feedback"
                  }
                }
              },
              "text/json": {
                "schema": {
                  "type": "array",
                  "items": {
                    "$ref": "#/components/schemas/Feedback"
                  }
                }
              }
            }
          }
        }
      },
      "post": {
        "tags": [
          "Feedback"
        ],
        "requestBody": {
          "content": {
            "application/json": {
              "schema": {
                "$ref": "#/components/schemas/Feedback"
              }
            },
            "text/json": {
              "schema": {
                "$ref": "#/components/schemas/Feedback"
              }
            },
            "application/*+json": {
              "schema": {
                "$ref": "#/components/schemas/Feedback"
              }
            }
          }
        },
        "responses": {
          "200": {
            "description": "OK",
            "content": {
              "text/plain": {
                "schema": {
                  "$ref": "#/components/schemas/Feedback"
                }
              },
              "application/json": {
                "schema": {
                  "$ref": "#/components/schemas/Feedback"
                }
              },
              "text/json": {
                "schema": {
                  "$ref": "#/components/schemas/Feedback"
                }
              }
            }
          }
        }
      }
    },
    "/api/Feedback/{id}": {
      "get": {
        "tags": [
          "Feedback"
        ],
        "parameters": [
          {
            "name": "id",
            "in": "path",
            "required": true,
            "schema": {
              "type": "integer",
              "format": "int32"
            }
          }
        ],
        "responses": {
          "200": {
            "description": "OK",
            "content": {
              "text/plain": {
                "schema": {
                  "$ref": "#/components/schemas/Feedback"
                }
              },
              "application/json": {
                "schema": {
                  "$ref": "#/components/schemas/Feedback"
                }
              },
              "text/json": {
                "schema": {
                  "$ref": "#/components/schemas/Feedback"
                }
              }
            }
          }
        }
      },
      "put": {
        "tags": [
          "Feedback"
        ],
        "parameters": [
          {
            "name": "id",
            "in": "path",
            "required": true,
            "schema": {
              "type": "integer",
              "format": "int32"
            }
          }
        ],
        "requestBody": {
          "content": {
            "application/json": {
              "schema": {
                "$ref": "#/components/schemas/Feedback"
              }
            },
            "text/json": {
              "schema": {
                "$ref": "#/components/schemas/Feedback"
              }
            },
            "application/*+json": {
              "schema": {
                "$ref": "#/components/schemas/Feedback"
              }
            }
          }
        },
        "responses": {
          "200": {
            "description": "OK",
            "content": {
              "text/plain": {
                "schema": {
                  "$ref": "#/components/schemas/Feedback"
                }
              },
              "application/json": {
                "schema": {
                  "$ref": "#/components/schemas/Feedback"
                }
              },
              "text/json": {
                "schema": {
                  "$ref": "#/components/schemas/Feedback"
                }
              }
            }
          }
        }
      },
      "delete": {
        "tags": [
          "Feedback"
        ],
        "parameters": [
          {
            "name": "id",
            "in": "path",
            "required": true,
            "schema": {
              "type": "integer",
              "format": "int32"
            }
          }
        ],
        "responses": {
          "200": {
            "description": "OK"
          }
        }
      }
    }
  },
  "components": {
    "schemas": {
      "Feedback": {
        "type": "object",
        "properties": {
          "id": {
            "type": "integer",
            "format": "int32"
          },
          "rating": {
            "maximum": 5,
            "minimum": 1,
            "type": "integer",
            "format": "int32"
          },
          "feedbackText": {
            "maxLength": 200,
            "type": "string",
            "nullable": true
          },
          "dateCreated": {
            "type": "string",
            "format": "date-time"
          },
          "userId": {
            "type": "string",
            "nullable": true
          },
          "userName": {
            "type": "string",
            "nullable": true
          },
          "location": {
            "type": "string",
            "nullable": true
          }
        },
        "additionalProperties": false
      }
    }
  }
}